selve/__init__.py
selve/commands.py
selve/commeo.py
selve/communication.py
selve/device.py
selve/group.py
selve/protocol.py
selve/utils.py
selve/commandClasses/__init__.py
selve/commandClasses/actor.py
selve/commandClasses/command.py
selve/commandClasses/common.py
selve/commandClasses/group.py
selve/commandClasses/iveo.py
selve/commandClasses/senSim.py
selve/commandClasses/sender.py
selve/commandClasses/sensor.py
python_selve_http-1.0.4.dist-info/LICENSE
python_selve_http-1.0.4.dist-info/METADATA
python_selve_http-1.0.4.dist-info/WHEEL
python_selve_http-1.0.4.dist-info/top_level.txt
python_selve_http-1.0.4.dist-info/RECORD
