Metadata-Version: 2.1
Name: python-selve-http
Version: 1.0.4
Summary: Python library for interfacing with selve devices using the USB-RF controller, hooked up with an HTTP server; forked from GPULIDO & Kannix2005
Home-page: https://github.com/gillesmaes/python-selve-http
Author: Stefan Altheimer
Author-email: stefan.altheimer@gmail.com
Keywords: selve blind awning shutter usb rf
Classifier: Development Status :: 3 - Alpha
Classifier: Intended Audience :: Developers
Classifier: Topic :: Software Development :: Build Tools
Classifier: License :: OSI Approved :: MIT License
Classifier: Programming Language :: Python :: 3
Classifier: Programming Language :: Python :: 3.4
Classifier: Programming Language :: Python :: 3.5
Classifier: Programming Language :: Python :: 3.6
License-File: LICENSE
Requires-Dist: requests
Requires-Dist: aiohttp
Requires-Dist: untangle
